__init__.py
server.py
todolist_mcp_server-0.1.1.dist-info/METADATA
todolist_mcp_server-0.1.1.dist-info/WHEEL
todolist_mcp_server-0.1.1.dist-info/entry_points.txt
todolist_mcp_server-0.1.1.dist-info/RECORD
