Metadata-Version: 2.3
Name: todolist-mcp-server
Version: 0.1.1
Summary: TodoList MCP Server - A Model Context Protocol server for managing todo lists
Author: GeeseDream
Author-email: GeeseDream@aliyun.com
Requires-Python: >=3.12
Classifier: Programming Language :: Python :: 3
Classifier: Programming Language :: Python :: 3.12
Classifier: Programming Language :: Python :: 3.13
Provides-Extra: dev
Requires-Dist: mcp[cli] (>=1.10.1,<2.0.0)
Requires-Dist: pyright (>=1.1.0) ; extra == "dev"
Requires-Dist: ruff (>=0.1.0) ; extra == "dev"
Project-URL: Homepage, https://cnb.cool/hicaosen/todolist
Project-URL: Repository, https://cnb.cool/hicaosen/todolist.git
